aiosip/protocol.py
aiosip/exceptions.py
aiosip/uri.py
aiosip/utils.py
aiosip/application.py
aiosip/log.py
aiosip/contact.py
aiosip/__init__.py
aiosip/call.py
aiosip/dialog.py
aiosip/auth.py
aiosip/param.py
aiosip/message.py
aiosip-0.2.0.dist-info/top_level.txt
aiosip-0.2.0.dist-info/METADATA
aiosip-0.2.0.dist-info/metadata.json
aiosip-0.2.0.dist-info/WHEEL
aiosip-0.2.0.dist-info/RECORD
aiosip-0.2.0.dist-info/DESCRIPTION.rst
