Metadata-Version: 2.0
Name: aiosip
Version: 0.2.0
Summary: SIP support for AsyncIO
Home-page: https://github.com/Eyepea/aiosip
Author: Ludovic Gasc (GMLudo)
Author-email: gmludo@gmail.com
License: Apache 2
Keywords: asyncio,sip,telephony
Platform: UNKNOWN
Classifier: Development Status :: 3 - Alpha
Classifier: Framework :: AsyncIO
Classifier: Intended Audience :: Developers
Classifier: License :: OSI Approved :: Apache Software License
Classifier: Natural Language :: English
Classifier: Programming Language :: Python :: 3
Classifier: Programming Language :: Python :: 3.3
Classifier: Programming Language :: Python :: 3.4
Classifier: Programming Language :: Python :: 3.5
Classifier: Programming Language :: Python :: 3.6
Classifier: Topic :: Communications
Classifier: Topic :: Communications :: Internet Phone
Classifier: Topic :: Communications :: Telephony
Requires-Dist: multidict (>=2.0)
Requires-Dist: pyquery
